syriantaxes/__init__.py
syriantaxes/bracket.py
syriantaxes/cast.py
syriantaxes/rounder.py
syriantaxes/ss.py
syriantaxes/taxes.py
syriantaxes/types.py
syriantaxes-0.1.0.dist-info/METADATA
syriantaxes-0.1.0.dist-info/WHEEL
syriantaxes-0.1.0.dist-info/entry_points.txt
syriantaxes-0.1.0.dist-info/RECORD
