Metadata-Version: 2.4
Name: syriantaxes
Version: 0.1.0
Summary: A Python package for calculating taxes and compensations for Syrian salaries based on Syrian tax laws.
Author-email: Abdullah Altatan <a.altatan@gmail.com>
Requires-Python: >=3.10
